chatnoir_pyterrier/__init__.py
chatnoir_pyterrier/feature.py
chatnoir_pyterrier/py.typed
chatnoir_pyterrier/retrieve.py
chatnoir_pyterrier-3.3.1.dist-info/licenses/LICENSE
examples/.gitignore
examples/__init__.py
examples/experiment.ipynb
examples/experiment.py
examples/ray-runtime-env.yml
examples/search.ipynb
examples/search_touche_2023.ipynb
tests/__init__.py
tests/conftest.py
tests/test_retrieve.py
chatnoir_pyterrier-3.3.1.dist-info/METADATA
chatnoir_pyterrier-3.3.1.dist-info/WHEEL
chatnoir_pyterrier-3.3.1.dist-info/top_level.txt
chatnoir_pyterrier-3.3.1.dist-info/RECORD
