Metadata-Version: 2.4
Name: chatnoir-pyterrier
Version: 3.3.1
Summary: Use the ChatNoir search engine in PyTerrier.
Author-email: Jan Heinrich Merker <heinrich.merker@uni-jena.de>
Project-URL: Homepage, https://github.com/chatnoir-eu/chatnoir-pyterrier
Project-URL: Bug Tracker, https://github.com/chatnoir-eu/chatnoir-pyterrier/issues
Classifier: Programming Language :: Python :: 3
Classifier: Programming Language :: Python :: 3 :: Only
Classifier: Programming Language :: Python :: 3.8
Classifier: Programming Language :: Python :: 3.9
Classifier: Programming Language :: Python :: 3.10
Classifier: Programming Language :: Python :: 3.11
Classifier: Programming Language :: Python :: 3.12
Classifier: License :: OSI Approved :: MIT License
Classifier: Operating System :: OS Independent
Classifier: Intended Audience :: Science/Research
Classifier: Topic :: Scientific/Engineering
Requires-Python: >=3.8
License-File: LICENSE
Requires-Dist: chatnoir-api~=3.3
Requires-Dist: importlib-metadata~=8.5
Requires-Dist: pandas~=2.0
Requires-Dist: python-terrier~=0.13.1
Requires-Dist: typing-extensions~=4.13
Provides-Extra: tests
Requires-Dist: bandit[toml]~=1.7; extra == "tests"
Requires-Dist: jupyter~=1.0; extra == "tests"
Requires-Dist: mypy~=1.13; extra == "tests"
Requires-Dist: pytest~=8.3; extra == "tests"
Requires-Dist: pytest-cov<8,>=5; extra == "tests"
Requires-Dist: ruff<0.14.0,>=0.7.1; extra == "tests"
Requires-Dist: types-requests~=2.32; extra == "tests"
Provides-Extra: experiment
Requires-Dist: pyterrier-caching~=0.6; extra == "experiment"
Requires-Dist: python-dotenv~=1.0; extra == "experiment"
Requires-Dist: ray[default]~=2.38; extra == "experiment"
Dynamic: license-file
